<?xml version="1.0" encoding="ISO-8859-1"?>
<root>
	<item id="Title"><![CDATA[Discuz! Plugin]]></item>
	<item id="Version"><![CDATA[X3.2]]></item>
	<item id="Time"><![CDATA[2015-01-19 09:11]]></item>
	<item id="From"><![CDATA[折翼天使资源社区 (http://www.www.zheyitianshi.com/)]]></item>
	<item id="Data">
		<item id="plugin">
			<item id="available"><![CDATA[1]]></item>
			<item id="adminid"><![CDATA[1]]></item>
			<item id="name"><![CDATA[微信全民红包营销]]></item>
			<item id="identifier"><![CDATA[hejin_hongbao]]></item>
			<item id="description"><![CDATA[]]></item>
			<item id="datatables"><![CDATA[]]></item>
			<item id="directory"><![CDATA[hejin_hongbao/]]></item>
			<item id="copyright"><![CDATA[折翼天使资源社区 www.zheyitianshi.com]]></item>
			<item id="version"><![CDATA[6.0]]></item>
			<item id="__modules">
				<item id="0">
					<item id="name"><![CDATA[hongbao]]></item>
					<item id="param"><![CDATA[]]></item>
					<item id="menu"><![CDATA[红包活动]]></item>
					<item id="url"><![CDATA[]]></item>
					<item id="type"><![CDATA[3]]></item>
					<item id="adminid"><![CDATA[0]]></item>
					<item id="displayorder"><![CDATA[0]]></item>
					<item id="navtitle"><![CDATA[]]></item>
					<item id="navicon"><![CDATA[]]></item>
					<item id="navsubname"><![CDATA[]]></item>
					<item id="navsuburl"><![CDATA[]]></item>
				</item>
				<item id="1">
					<item id="name"><![CDATA[zhushou]]></item>
					<item id="param"><![CDATA[]]></item>
					<item id="menu"><![CDATA[运营思路]]></item>
					<item id="url"><![CDATA[]]></item>
					<item id="type"><![CDATA[3]]></item>
					<item id="adminid"><![CDATA[0]]></item>
					<item id="displayorder"><![CDATA[1]]></item>
					<item id="navtitle"><![CDATA[]]></item>
					<item id="navicon"><![CDATA[]]></item>
					<item id="navsubname"><![CDATA[]]></item>
					<item id="navsuburl"><![CDATA[]]></item>
				</item>
			</item>
		</item>
		<item id="version"><![CDATA[X2.5,X3,X3.1,X3.2]]></item>
		<item id="var">
			<item id="0">
				<item id="displayorder"><![CDATA[1]]></item>
				<item id="title"><![CDATA[设置分享链接]]></item>
				<item id="description"><![CDATA[分享出去的链接类型：
1、打开直接为红包领取页
2、打开为引导关注参与活动页面]]></item>
				<item id="variable"><![CDATA[hjhb_fxurl]]></item>
				<item id="type"><![CDATA[select]]></item>
				<item id="value"><![CDATA[2]]></item>
				<item id="extra"><![CDATA[1=红包链接
2=引导关注链接]]></item>
			</item>
			<item id="1">
				<item id="displayorder"><![CDATA[2]]></item>
				<item id="title"><![CDATA[红包领取页底部说明（一）]]></item>
				<item id="description"><![CDATA[]]></item>
				<item id="variable"><![CDATA[hjhb_hblqdba]]></item>
				<item id="type"><![CDATA[text]]></item>
				<item id="value"><![CDATA[活动期内每天都可以领取一个私藏红包]]></item>
				<item id="extra"><![CDATA[]]></item>
			</item>
			<item id="2">
				<item id="displayorder"><![CDATA[3]]></item>
				<item id="title"><![CDATA[红包领取页底部说明（二）]]></item>
				<item id="description"><![CDATA[]]></item>
				<item id="variable"><![CDATA[hjhb_hblqdbb]]></item>
				<item id="type"><![CDATA[text]]></item>
				<item id="value"><![CDATA[领取多多，积累多多，明天记得来哦]]></item>
				<item id="extra"><![CDATA[]]></item>
			</item>
			<item id="3">
				<item id="displayorder"><![CDATA[4]]></item>
				<item id="title"><![CDATA[分享得红包页描述]]></item>
				<item id="description"><![CDATA[]]></item>
				<item id="variable"><![CDATA[hjhb_fxdhbms]]></item>
				<item id="type"><![CDATA[text]]></item>
				<item id="value"><![CDATA[分享红包，小伙伴点击即得分享奖励！]]></item>
				<item id="extra"><![CDATA[]]></item>
			</item>
			<item id="4">
				<item id="displayorder"><![CDATA[5]]></item>
				<item id="title"><![CDATA[兑换说明补充]]></item>
				<item id="description"><![CDATA[抢到的红包页面下方的兑换说明的补充！
每行用<p></p>包围
如：<p>4.兑换说明补充</p>
支持html代码，可放图片或者链接]]></item>
				<item id="variable"><![CDATA[hjhb_duihuansm]]></item>
				<item id="type"><![CDATA[textarea]]></item>
				<item id="value"><![CDATA[<p><a href="http://bbs.weixinhj.com">兑换补充说明</a></p>]]></item>
				<item id="extra"><![CDATA[]]></item>
			</item>
			<item id="5">
				<item id="displayorder"><![CDATA[6]]></item>
				<item id="title"><![CDATA[分享浏览量排行榜标题]]></item>
				<item id="description"><![CDATA[]]></item>
				<item id="variable"><![CDATA[hjhb_sharephb]]></item>
				<item id="type"><![CDATA[text]]></item>
				<item id="value"><![CDATA[分享浏览量排行榜]]></item>
				<item id="extra"><![CDATA[]]></item>
			</item>
			<item id="6">
				<item id="displayorder"><![CDATA[7]]></item>
				<item id="title"><![CDATA[分享浏览量排行榜显示前几名]]></item>
				<item id="description"><![CDATA[]]></item>
				<item id="variable"><![CDATA[hjhb_sharephbnub]]></item>
				<item id="type"><![CDATA[number]]></item>
				<item id="value"><![CDATA[5]]></item>
				<item id="extra"><![CDATA[]]></item>
			</item>
		</item>
		<item id="language">
			<item id="scriptlang">
				<item id="addstok"><![CDATA[添加成功]]></item>
				<item id="picgsbd"><![CDATA[图片格式不正确，只支持jpg,jpeg,gif,png格式]]></item>
				<item id="tjcg"><![CDATA[推荐成功！]]></item>
				<item id="qxtjcg"><![CDATA[取消推荐成功！]]></item>
				<item id="delcg"><![CDATA[删除成功！]]></item>
				<item id="setzjok"><![CDATA[成功设置中奖]]></item>
				<item id="setzjno"><![CDATA[此用户已中奖，请不要重复设置]]></item>
				<item id="qxzjok"><![CDATA[成功取消中奖]]></item>
				<item id="qxzjno"><![CDATA[此用户未中奖，无法取消]]></item>
				<item id="zongjrs"><![CDATA[中奖人数已经达到]]></item>
				<item id="zongjrsa"><![CDATA[人，不能再增加！]]></item>
				<item id="bjlqok"><![CDATA[成功标记为已领取状态]]></item>
				<item id="bjlqno"><![CDATA[成功标记为已领取状态]]></item>
				<item id="shanchuts"><![CDATA[你确定要删除此条记录吗？]]></item>
				<item id="nowzjyh"><![CDATA[没有未中奖用户]]></item>
				<item id="gong"><![CDATA[共]]></item>
				<item id="ye"><![CDATA[页]]></item>
				<item id="shouyephp"><![CDATA[首页]]></item>
				<item id="shangyiye"><![CDATA[上一页]]></item>
				<item id="xiayiye"><![CDATA[下一页]]></item>
				<item id="moye"><![CDATA[末页]]></item>
				<item id="over"><![CDATA[活动已经结束！]]></item>
				<item id="yiduihuan"><![CDATA[您已兑换过现金券！一次活动仅允许兑换一张现金券！]]></item>
			</item>
			<item id="templatelang">
				<item id="shanchuts"><![CDATA[你确定要删除此条记录吗？]]></item>
				<item id="sharemc"><![CDATA[活动名称]]></item>
				<item id="sharelb"><![CDATA[红包活动列表]]></item>
				<item id="sharegl"><![CDATA[活动管理]]></item>
				<item id="tjshare"><![CDATA[添加活动]]></item>
				<item id="hbpic"><![CDATA[红包标志图片]]></item>
				<item id="wxpic"><![CDATA[微信分享图片]]></item>
				<item id="hbpicym"><![CDATA[源码下载]]></item>
				<item id="hbpicts"><![CDATA[不上传则使用空白红包，请下载源码增加标志后上传，请上传png透明图片！]]></item>
				<item id="wxname"><![CDATA[微信分享标题]]></item>
				<item id="wxurl"><![CDATA[微信分享活动引导链接]]></item>
				<item id="wxurltsa"><![CDATA[查看范例]]></item>
				<item id="wxurltsb"><![CDATA[资源源码下载]]></item>
				<item id="descr"><![CDATA[简单描述]]></item>
				<item id="descrts"><![CDATA[如：11月20日-12月30日疯狂抢不停！]]></item>
				<item id="upnumber"><![CDATA[红包兑换物品的最低额度（以元为单位）]]></item>
				<item id="upnumberts"><![CDATA[即红包达到多少元才能兑换物品,活动期内每个用户只能兑换一个！注意：添加后无法修改！]]></item>
				<item id="hongbaonum"><![CDATA[分享即得的红包金额（以元为单位）]]></item>
				<item id="hongbaonumts"><![CDATA[即用户分享后，朋友点击进入才算分享成功！成功后赠送的红包金额]]></item>
				<item id="hongbaosj"><![CDATA[红包随机额度范围（以分为单位 100分=1元）]]></item>
				<item id="hongbaosjts"><![CDATA[每日每用户领取红包的随机额度（前一个为最低额度，后一个为最高额度）]]></item>
				<item id="allmomey"><![CDATA[本次活动现金限额（以元为单位）]]></item>
				<item id="allmomeyts"><![CDATA[即本次活动赠送出去的现金量，达到限额活动自动停止]]></item>
				<item id="paixu"><![CDATA[排序]]></item>
				<item id="isshow"><![CDATA[是否显示活动]]></item>
				<item id="iswqlb"><![CDATA[详情中是否显示平台宣传图片]]></item>
				<item id="iswqlbts"><![CDATA[此活动详情中是否显示平台宣传图片]]></item>
				<item id="baocun"><![CDATA[保存]]></item>
				<item id="jianyicc"><![CDATA[图片推荐尺寸]]></item>
				<item id="descinfo"><![CDATA[活动描述]]></item>
				<item id="descinfots"><![CDATA[（为了美观建议使用上方的活动描述图片）]]></item>
				<item id="starttime"><![CDATA[活动开始时间]]></item>
				<item id="endtime"><![CDATA[活动结束时间]]></item>
				<item id="xnclick"><![CDATA[起始虚拟浏览量]]></item>
				<item id="xnclickts"><![CDATA[为降低服务器压力！浏览量为：起始虚拟浏览量+虚拟增加频率]]></item>
				<item id="xnshares"><![CDATA[起始虚拟分享数]]></item>
				<item id="zsshares"><![CDATA[分享记录]]></item>
				<item id="xnsharests"><![CDATA[分享数为：起始虚拟分享数+真实分享数]]></item>
				<item id="addstmsga"><![CDATA[不能为空]]></item>
				<item id="addstmsgb"><![CDATA[不能超过1000字符]]></item>
				<item id="addstmsgc"><![CDATA[试题简介不能为空]]></item>
				<item id="addstmsgd"><![CDATA[不能超过10000字符]]></item>
				<item id="addstmsge"><![CDATA[不能为空]]></item>
				<item id="addstmsgf"><![CDATA[必须是数字]]></item>
				<item id="addstmsgg"><![CDATA[数字必须在0-10000之间]]></item>
				<item id="liulana"><![CDATA[预览]]></item>
				<item id="bianji"><![CDATA[编辑]]></item>
				<item id="shanchu"><![CDATA[删除]]></item>
				<item id="hjguanli"><![CDATA[查看兑换]]></item>
				<item id="caozuo"><![CDATA[操作]]></item>
				<item id="huodonggl"><![CDATA[红包活动管理]]></item>
				<item id="huodonglb"><![CDATA[红包活动]]></item>
				<item id="addhd"><![CDATA[添加活动]]></item>
				<item id="huojiang"><![CDATA[兑换记录]]></item>
				<item id="hdwjs"><![CDATA[活动未结束]]></item>
				<item id="shareuser"><![CDATA[分享用户]]></item>
				<item id="wenxints"><![CDATA[温馨提示：]]></item>
				<item id="liulan"><![CDATA[浏览：]]></item>
				<item id="fenxiang"><![CDATA[分享：]]></item>
				<item id="kongge"><![CDATA[　]]></item>
				<item id="jplist"><![CDATA[奖品列表]]></item>
				<item id="endtimea"><![CDATA[截止时间]]></item>
				<item id="yijinjs"><![CDATA[已经结束]]></item>
				<item id="shuliang"><![CDATA[数量：]]></item>
				<item id="shareok"><![CDATA[转发成功]]></item>
				<item id="dianjiwm"><![CDATA[再点关注我们，得获奖信息]]></item>
				<item id="qsrndsjh"><![CDATA[请输入您的手机号码]]></item>
				<item id="qsrndsjha"><![CDATA[请输入您的手机号码，以便统计您的红包总额！]]></item>
				<item id="canyuhd"><![CDATA[放入我的口袋]]></item>
				<item id="djljcybhd"><![CDATA[点击立即参与本活动]]></item>
				<item id="guanzhu"><![CDATA[关注]]></item>
				<item id="nologin"><![CDATA[未登录]]></item>
				<item id="chengong"><![CDATA[成功]]></item>
				<item id="weizhuan"><![CDATA[未转]]></item>
				<item id="yizhuan"><![CDATA[已转]]></item>
				<item id="kjdjs"><![CDATA[开奖倒计: ]]></item>
				<item id="jxtjz"><![CDATA[奖项统计中...]]></item>
				<item id="yijies"><![CDATA[往期活动]]></item>
				<item id="yijiesa"><![CDATA[已结束]]></item>
				<item id="weikais"><![CDATA[未开始]]></item>
				<item id="shouye"><![CDATA[首页]]></item>
				<item id="jinxingz"><![CDATA[进行中]]></item>
				<item id="qxcjmm"><![CDATA[请先创建密码]]></item>
				<item id="chuangjianmm"><![CDATA[您的账号未创建登录密码，是否现在创建？]]></item>
				<item id="cjmima"><![CDATA[创建密码]]></item>
				<item id="cjmimaa"><![CDATA[请在这里创建您的登录密码]]></item>
				<item id="xiugaimm"><![CDATA[修改密码]]></item>
				<item id="xiugaimma"><![CDATA[请在这里修改您的账号密码]]></item>
				<item id="loginout"><![CDATA[退出登录]]></item>
				<item id="maohao"><![CDATA[：]]></item>
				<item id="shoujihao"><![CDATA[手　机　号]]></item>
				<item id="shoujihaoa"><![CDATA[手机号]]></item>
				<item id="shoujihaob"><![CDATA[手机号码]]></item>
				<item id="dlmimab"><![CDATA[密　码]]></item>
				<item id="dlmima"><![CDATA[新登录密码]]></item>
				<item id="dlmimaa"><![CDATA[请输入新登录密码]]></item>
				<item id="dlmimac"><![CDATA[未创建密码无需输入]]></item>
				<item id="jdlmima"><![CDATA[旧登录密码]]></item>
				<item id="jdlmimaa"><![CDATA[请输入旧登录密码]]></item>
				<item id="cfmima"><![CDATA[重复新密码]]></item>
				<item id="cfmimaa"><![CDATA[请重复新的登录密码]]></item>
				<item id="cjdlmm"><![CDATA[创建登录密码]]></item>
				<item id="xgdlmm"><![CDATA[修改登录密码]]></item>
				<item id="ljdenglu"><![CDATA[立即登录]]></item>
				<item id="meiyouzh"><![CDATA[没有账号？参与一次活动拥有账号，快去参与吧！]]></item>
				<item id="zhongkhz"><![CDATA[【]]></item>
				<item id="zhongkhy"><![CDATA[】]]></item>
				<item id="dlsjgzmc"><![CDATA[独立商家公众名称]]></item>
				<item id="dlsjgzmcts"><![CDATA[活动特定的商家公众，不填写则为官方微信公众]]></item>
				<item id="dlsjgzurl"><![CDATA[独立商家公众引导关注链接]]></item>
				<item id="fxjljfs"><![CDATA[分享奖励积分数]]></item>
				<item id="fxjljfsts"><![CDATA[分享成功后奖励给用户的积分数]]></item>
				<item id="editpicts"><![CDATA[不修改则无需上传]]></item>
				<item id="yqguize"><![CDATA[领取说明]]></item>
				<item id="jutisma"><![CDATA[只要分享您就有机会获得它！]]></item>
				<item id="yqguizets"><![CDATA[显示在我的现金券页面，每行请用 P 标签包围]]></item>
				<item id="shareuserlist"><![CDATA[分享用户记录]]></item>
				<item id="zjuserlist"><![CDATA[中奖用户列表]]></item>
				<item id="shareclick"><![CDATA[分享浏览次数]]></item>
				<item id="sharetime"><![CDATA[分享时间]]></item>
				<item id="neidingzj"><![CDATA[中奖设置]]></item>
				<item id="yizhongj"><![CDATA[已中奖]]></item>
				<item id="sjzhongj"><![CDATA[设置中奖]]></item>
				<item id="sjzhongjts"><![CDATA[确定要将此用户设定为中奖用户？]]></item>
				<item id="qxzhongjts"><![CDATA[确定要取消此用户的中奖记录吗？]]></item>
				<item id="qxzhongj"><![CDATA[取消中奖]]></item>
				<item id="zhuangtai"><![CDATA[状态]]></item>
				<item id="weilq"><![CDATA[未领取]]></item>
				<item id="yilq"><![CDATA[已领取]]></item>
				<item id="biaojiwylq"><![CDATA[标记为已领取]]></item>
				<item id="biaojiwylqts"><![CDATA[您确定要设置为奖品已领取状态吗？]]></item>
				<item id="suijihuoqu"><![CDATA[随机抽取一条记录]]></item>
				<item id="cxsuiji"><![CDATA[重新随机抽取]]></item>
				<item id="fhfxlb"><![CDATA[返回分享列表]]></item>
				<item id="wodejp"><![CDATA[我的奖品]]></item>
				<item id="weilqjp"><![CDATA[未领取奖品：]]></item>
				<item id="yilqjp"><![CDATA[; 已领取奖品：]]></item>
				<item id="yizhongja"><![CDATA[已中奖]]></item>
				<item id="lianxidh"><![CDATA[TEL：]]></item>
				<item id="weizj"><![CDATA[未中奖]]></item>
				<item id="jxzdhd"><![CDATA[进行中的活动]]></item>
				<item id="moreshare"><![CDATA[更多惊喜]]></item>
				<item id="moresharea"><![CDATA[是否要参与更多活动？]]></item>
				<item id="lingguoa"><![CDATA[今天的私藏红包已经领过喽~]]></item>
				<item id="lingguob"><![CDATA[每天只有一份，明天再来吧]]></item>
				<item id="qiangdaoa"><![CDATA[抢到1个红包]]></item>
				<item id="yifangru"><![CDATA[已放入你的口袋]]></item>
				<item id="meitiany"><![CDATA[活动期内每天都可以领取一个私藏红包]]></item>
				<item id="meitianb"><![CDATA[领取多多，积累多多，明天记得来哦]]></item>
				<item id="qiangddhb"><![CDATA[抢到的红包]]></item>
				<item id="fachudhb"><![CDATA[分享得红包]]></item>
				<item id="wodexjq"><![CDATA[我的]]></item>
				<item id="wodehbze"><![CDATA[我的红包总额]]></item>
				<item id="yuan"><![CDATA[元]]></item>
				<item id="qiangdao"><![CDATA[抢到]]></item>
				<item id="duihuansm"><![CDATA[兑换说明：]]></item>
				<item id="duihuana"><![CDATA[1.红包金额达到]]></item>
				<item id="duihuanb"><![CDATA[元即可兑换]]></item>
				<item id="duihuane"><![CDATA[2.活动期间一人只能兑换一次]]></item>
				<item id="duihuanc"><![CDATA[3.当红包金额不足]]></item>
				<item id="duihuand"><![CDATA[元时，记得天天来领红包哦]]></item>
				<item id="mycash"><![CDATA[我的现金券]]></item>
				<item id="nomycasha"><![CDATA[你还没有兑换]]></item>
				<item id="nomycashb"><![CDATA[请查看我抢到的红包]]></item>
				<item id="nomycashc"><![CDATA[满额即可兑换]]></item>
				<item id="nomycashd"><![CDATA[元]]></item>
				<item id="upnumpic"><![CDATA[兑换物品图片]]></item>
				<item id="xjqym"><![CDATA[提供的源码为5元现金券源码，可以下载后修改，然后上传，务必为透明背景！]]></item>
				<item id="fachudehb"><![CDATA[发出的红包]]></item>
				<item id="fxjdhb"><![CDATA[发红包即得]]></item>
				<item id="fxjdhba"><![CDATA[元红包]]></item>
				<item id="fxjdhbb"><![CDATA[分享红包，朋友点击即送！]]></item>
				<item id="haoyoulll"><![CDATA[分享好友浏览量]]></item>
				<item id="fxdhb"><![CDATA[分享]]></item>
				<item id="wfengx"><![CDATA[未分享]]></item>
				<item id="chenggong"><![CDATA[成功]]></item>
				<item id="yihuode"><![CDATA[已获得]]></item>
				<item id="haoyoullla"><![CDATA[好友浏览量：]]></item>
				<item id="yifenx"><![CDATA[分享到朋友圈]]></item>
				<item id="yongudj"><![CDATA[朋友点击后您将获得]]></item>
				<item id="upname"><![CDATA[红包兑换的物品名称]]></item>
				<item id="upnamets"><![CDATA[比如商家现金券、油卡、压岁钱（现金）等]]></item>
				<item id="dhname"><![CDATA[可兑换物品]]></item>
				<item id="dhnamea"><![CDATA[兑换物品]]></item>
				<item id="qiyong"><![CDATA[启用]]></item>
				<item id="guanbi"><![CDATA[关闭]]></item>
				<item id="hdzjine"><![CDATA[活动总金额]]></item>
				<item id="mrmrhbsj"><![CDATA[红包随机金额]]></item>
				<item id="duihuanjl"><![CDATA[兑换记录]]></item>
				<item id="dhtime"><![CDATA[兑换时间]]></item>
				<item id="jiazhi"><![CDATA[价值]]></item>
				<item id="yishiyong"><![CDATA[已领取]]></item>
				<item id="weilinqu"><![CDATA[未领取（请查看下方的领取说明）]]></item>
				<item id="syqueren"><![CDATA[领取确认]]></item>
				<item id="zongdhje"><![CDATA[总兑换金额]]></item>
				<item id="linqujl"><![CDATA[领取记录]]></item>
				<item id="yonghujl"><![CDATA[用户记录]]></item>
				<item id="hdzhuangt"><![CDATA[活动状态]]></item>
				<item id="allyonghu"><![CDATA[所有用户]]></item>
				<item id="linhbyh"><![CDATA[领红包用户]]></item>
				<item id="yonghu"><![CDATA[用户]]></item>
				<item id="linquzje"><![CDATA[领取总金额]]></item>
				<item id="duihuanzt"><![CDATA[兑换状态]]></item>
				<item id="yiduihuana"><![CDATA[已兑换]]></item>
				<item id="weiduihuan"><![CDATA[未兑换]]></item>
				<item id="xianyouje"><![CDATA[现有金额]]></item>
				<item id="gzurl"><![CDATA[放置到公众平台的活动链接模式：]]></item>
				<item id="yuming"><![CDATA[论坛网址]]></item>
				<item id="huodongid"><![CDATA[[活动ID]]]></item>
				<item id="yishiyongts"><![CDATA[确定要将此记录设置为已领取吗？]]></item>
				<item id="lllpmdijl"><![CDATA[分享浏览量排名第一者，将获得]]></item>
				<item id="fxllone"><![CDATA[分享浏览排名第一奖励]]></item>
				<item id="fxllonets"><![CDATA[活动结束后分享出去的浏览量排名第一者获得的奖品名称]]></item>
				<item id="pcurlts"><![CDATA[此为活动链接！移动端打开会自动识别！]]></item>
				<item id="allyx"><![CDATA[微信游戏营销平台]]></item>
				<item id="allyxinfo"><![CDATA[整合游戏插件功能 可添加外链活动 可添加专辑、广告完美的微信分享，分享给特定好友、分享到朋友圈]]></item>
				<item id="share"><![CDATA[微信分享抽奖营销]]></item>
				<item id="shareinfo"><![CDATA[完美的运营流程，公众关注爆炸式增长！后台清晰的分享记录，真正掌握增长趋势！]]></item>
				<item id="zazhi"><![CDATA[微信杂志广告营销]]></item>
				<item id="zazhiinfo"><![CDATA[可添加无数杂志广告,各自可以添加无数的分页 分页类型多模式化：大图模式、视频模式、联系模式完美支持任意元素自定义：封页、蒙版、音乐等完美的微信分享，分享给特定好友、分享到朋友圈]]></item>
				<item id="pthd"><![CDATA[微信九宫图营销]]></item>
				<item id="pthdinfo"><![CDATA[可添加无数九宫图拼图活动 可设置分享后才能提交成绩，病毒式传播！ 清晰的排行榜，排名一览无余！完美的微信分享，分享给特定好友、分享到朋友圈]]></item>
				<item id="pintu"><![CDATA[微信广告拼图营销]]></item>
				<item id="pintuinfo"><![CDATA[可添加无数拼图闯关活动，各自可添加无数关卡 可设置奖励时间区间：每日奖励、活动截止奖励 可设置奖励人数完美的微信分享，分享给特定好友、分享到朋友圈]]></item>
				<item id="wxyx"><![CDATA[微信测试考试类营销]]></item>
				<item id="wxyxinfo"><![CDATA[测试类的微信营销 例如：爱情测试、性格测试等等 试题类的微信营销 例如：本地方言考试等等 自定义背景，自定义分享图标等等可推荐置顶好的试题或测试问题]]></item>
				<item id="forms"><![CDATA[移动&PC万能报名]]></item>
				<item id="formsinfo"><![CDATA[自动识别电脑版和手机版，支持自定义任意表单模型、自定义字段]]></item>
				<item id="vheka"><![CDATA[微信微贺卡营销]]></item>
				<item id="vhekainfo"><![CDATA[可添加无数分类、贺卡样式（支持背景音乐）一张图片、一段文字，定义出完美贺卡样式]]></item>
				<item id="vcard"><![CDATA[微信微名片营销]]></item>
				<item id="vcardinfo"><![CDATA[品牌化的微名片平台、病毒式微信传播模式、获取有用的用户资料]]></item>
				<item id="ceshia"><![CDATA[微信趣味测试营销]]></item>
				<item id="ceshiinfo"><![CDATA[支持设置关注链接、广告代码、联盟广告；完美的微信分享，分享给特定好友、分享到朋友圈]]></item>
				<item id="daohang"><![CDATA[微信万能导航营销]]></item>
				<item id="daohanginfo"><![CDATA[可制作任何类型的导航平台：如微信公众导航、商家网址导航等]]></item>
				<item id="test"><![CDATA[微信图文语音测试]]></item>
				<item id="testinfo"><![CDATA[可以添加3种不同模式、不同模版的测试!图文测试类、图文考试类、语音测试类]]></item>
				<item id="vote"><![CDATA[微信活动投票营销]]></item>
				<item id="voteinfo"><![CDATA[用户可在线报名,投一票即得一张刮刮卡]]></item>
				<item id="helps"><![CDATA[微信助力活动营销]]></item>
				<item id="helpsinfo"><![CDATA[增粉神器！]]></item>
			</item>
		</item>
		<item id="installfile"><![CDATA[install.php]]></item>
		<item id="uninstallfile"><![CDATA[uninstall.php]]></item>
	</item>
</root>